hbs/__init__.py
hbs/boundary.py
hbs/conformal_welding.py
hbs/hbs.py
hbs/mesh.py
hbs/qc/__init__.py
hbs/qc/bc.py
hbs/qc/lsqc.py
hbs/utils/__init__.py
hbs/utils/boundary.py
hbs/utils/geodesic_welding.py
hbs/utils/mobius.py
hbs/utils/poisson.py
hbs/utils/tool_functions.py
hbs/utils/zipper.py
hbs-1.0.0.dist-info/METADATA
hbs-1.0.0.dist-info/WHEEL
hbs-1.0.0.dist-info/top_level.txt
hbs-1.0.0.dist-info/RECORD
