Metadata-Version: 2.1
Name: hbs
Version: 1.0.0
Summary: Python library for computing Harmonic Beltrami Signature(HBS)
Home-page: https://github.com/ChanceAroundYou/hbs_python
Author: Lin Chenran
Author-email: chenranlin.17@gmail.com
Classifier: Programming Language :: Python :: 3
Classifier: License :: OSI Approved :: MIT License
Classifier: Operating System :: OS Independent
Requires-Python: >=3.8
Requires-Dist: numpy
Requires-Dist: scipy
Requires-Dist: matplotlib
Requires-Dist: opencv-python
